gtimes/__init__.py
gtimes/exceptions.py
gtimes/gpstime.py
gtimes/timecalc.py
gtimes/timefunc.py
gtimes-0.4.1.dist-info/METADATA
gtimes-0.4.1.dist-info/WHEEL
gtimes-0.4.1.dist-info/entry_points.txt
gtimes-0.4.1.dist-info/licenses/LICENSE
gtimes-0.4.1.dist-info/RECORD
