Metadata-Version: 2.4
Name: gtimes
Version: 0.4.1
Summary: High-precision GPS time conversion and processing library for GNSS applications
Project-URL: Homepage, https://github.com/bennigo/gtimes
Project-URL: Documentation, https://bennigo.github.io/gtimes
Project-URL: Repository, https://github.com/bennigo/gtimes
Project-URL: Issues, https://github.com/bennigo/gtimes/issues
Project-URL: Changelog, https://github.com/bennigo/gtimes/blob/main/CHANGELOG.md
Project-URL: Bug Tracker, https://github.com/bennigo/gtimes/issues
Project-URL: Source Code, https://github.com/bennigo/gtimes
Project-URL: CI/CD, https://github.com/bennigo/gtimes/actions
Project-URL: Coverage, https://codecov.io/gh/bennigo/gtimes
Author-email: Benedikt Gunnar Ófeigsson <bgo@vedur.is>, Maria Fernanda Gonzalez <mariagr@vedur.is>
Maintainer-email: Benedikt Gunnar Ófeigsson <bgo@vedur.is>
License: MIT
License-File: LICENSE
Keywords: conversion,coordinate-systems,gamit,geodesy,geophysics,globk,gnss,gps,leap-seconds,positioning,rinex,satellite-navigation,surveying,time
Classifier: Development Status :: 4 - Beta
Classifier: Environment :: Console
Classifier: Intended Audience :: Developers
Classifier: Intended Audience :: Science/Research
Classifier: License :: OSI Approved :: MIT License
Classifier: Natural Language :: English
Classifier: Operating System :: OS Independent
Classifier: Programming Language :: Python :: 3
Classifier: Programming Language :: Python :: 3.8
Classifier: Programming Language :: Python :: 3.9
Classifier: Programming Language :: Python :: 3.10
Classifier: Programming Language :: Python :: 3.11
Classifier: Programming Language :: Python :: 3.12
Classifier: Programming Language :: Python :: 3.13
Classifier: Topic :: Scientific/Engineering :: Astronomy
Classifier: Topic :: Scientific/Engineering :: GIS
Classifier: Topic :: Scientific/Engineering :: Physics
Classifier: Topic :: Software Development :: Libraries :: Python Modules
Classifier: Topic :: Utilities
Requires-Python: >=3.8
Requires-Dist: python-dateutil>=2.9.0
Provides-Extra: all
Requires-Dist: bandit>=1.7.0; extra == 'all'
Requires-Dist: beautifulsoup4>=4.12.0; extra == 'all'
Requires-Dist: black>=23.0.0; extra == 'all'
Requires-Dist: interrogate>=1.5.0; extra == 'all'
Requires-Dist: mkdocs-gen-files>=0.5.0; extra == 'all'
Requires-Dist: mkdocs-literate-nav>=0.6.0; extra == 'all'
Requires-Dist: mkdocs-material>=9.0.0; extra == 'all'
Requires-Dist: mkdocs-section-index>=0.3.0; extra == 'all'
Requires-Dist: mkdocs>=1.5.0; extra == 'all'
Requires-Dist: mkdocstrings[python]>=0.24.0; extra == 'all'
Requires-Dist: mypy>=1.0.0; extra == 'all'
Requires-Dist: pip-audit>=2.6.0; extra == 'all'
Requires-Dist: pipdeptree>=2.9.0; extra == 'all'
Requires-Dist: pydocstyle>=6.3.0; extra == 'all'
Requires-Dist: pytest-benchmark>=4.0.0; extra == 'all'
Requires-Dist: pytest-cov>=4.0.0; extra == 'all'
Requires-Dist: pytest-xdist>=3.0.0; extra == 'all'
Requires-Dist: pytest>=7.0.0; extra == 'all'
Requires-Dist: requests>=2.31.0; extra == 'all'
Requires-Dist: ruff>=0.1.0; extra == 'all'
Requires-Dist: safety>=2.0.0; extra == 'all'
Provides-Extra: dev
Requires-Dist: bandit>=1.7.0; extra == 'dev'
Requires-Dist: black>=23.0.0; extra == 'dev'
Requires-Dist: mypy>=1.0.0; extra == 'dev'
Requires-Dist: pytest-benchmark>=4.0.0; extra == 'dev'
Requires-Dist: pytest-cov>=4.0.0; extra == 'dev'
Requires-Dist: pytest>=7.0.0; extra == 'dev'
Requires-Dist: ruff>=0.1.0; extra == 'dev'
Requires-Dist: safety>=2.0.0; extra == 'dev'
Provides-Extra: docs
Requires-Dist: mkdocs-gen-files>=0.5.0; extra == 'docs'
Requires-Dist: mkdocs-literate-nav>=0.6.0; extra == 'docs'
Requires-Dist: mkdocs-material>=9.0.0; extra == 'docs'
Requires-Dist: mkdocs-section-index>=0.3.0; extra == 'docs'
Requires-Dist: mkdocs>=1.5.0; extra == 'docs'
Requires-Dist: mkdocstrings[python]>=0.24.0; extra == 'docs'
Provides-Extra: quality
Requires-Dist: beautifulsoup4>=4.12.0; extra == 'quality'
Requires-Dist: interrogate>=1.5.0; extra == 'quality'
Requires-Dist: pip-audit>=2.6.0; extra == 'quality'
Requires-Dist: pipdeptree>=2.9.0; extra == 'quality'
Requires-Dist: pydocstyle>=6.3.0; extra == 'quality'
Requires-Dist: requests>=2.31.0; extra == 'quality'
Provides-Extra: test
Requires-Dist: pytest-benchmark>=4.0.0; extra == 'test'
Requires-Dist: pytest-cov>=4.0.0; extra == 'test'
Requires-Dist: pytest-xdist>=3.0.0; extra == 'test'
Requires-Dist: pytest>=7.0.0; extra == 'test'
